Workbook

Sheet Items
A1: Параметры | B1: Описание | C1: Тип | D1: Сценарий
D2: Базовый | E2: Оптимистичный | F2: Пессимистичный
A3: Комиссия | B3: Процент с каждой сделки | C3: Переменные | D3: 0.1 | E3: 0.15 | F3: 0.07
A4: Средняя сумма сделки | B4: Средняя стоимость NFT-сделки | C4: Переменные | D4: 10 | E4: 12 | F4: 8
A5: Кол-во транзакций в месяц | B5: Число продаж/покупок NFT в месяц | C5: Переменные | D5: 10000 | E5: 15000 | F5: 6000
A6: Цена билета | B6: Средняя цена билета на выставку | C6: Постоянные | D6: 500 | E6: 1000 | F6: 300
A7: Билеты | B7: Сумма проданных билетов на одну выставку | C7: Переменные | D7: 100 | E7: 150 | F7: 80
A8: Хостинг в месяц | B8: Размещение сайта в интернете | C8: Постоянные | D8: 50 | E8: 30 | F8: 80
A9: Разработка сайта | B9: Разовая стоимость разработки | C9: Постоянные | D9: 3000 | E9: 2000 | F9: 4000
A10: Разработка смарт-контрактов | B10: Разовая стоимость разработки смарт-контрактов | C10: Постоянные | D10: 2000 | E10: 1000 | F10: 3000
A11: Деплой смарт-контрактов | B11: Стоимость деплоя | C11: Постоянные | D11: 500 | E11: 300 | F11: 800
A12: Маркетинг | B12: Стоимость продвижения в месяц | C12: Постоянные | D12: 1000 | E12: 800 | F12: 1500
A13: IT персонал | B13: Стоимость IT реализаций и поддержки в месяц | C13: Постоянные | D13: 3000 | E13: 2000 | F13: 5000
A14: Аренда | B14: Аренда помещения для хранения картин в месяц | C14: Постоянные | D14: 700 | E14: 400 | F14: 1500
... A23: Выставки | B23: Кол-во выставок в год | C23: Постоянные | D23: 2 | E23: 3 | F23: 1

Sheet Income
A1: Планируемые доходы, USD
B3: Январь | C3: Февраль | D3: Март | E3: Апрель | F3: Май | G3: Июнь | H3: Июль | I3: Август | J3: Сентябрь | K3: Октябрь | L3: Ноябрь | M3: Декабрь
A4: Комиссии за сделки | B4: =Items!D3 * Items!D4 * Items!D5 -> 10000 | C4: =B4*1.05 -> 10500 | D4: =C4*1.05 -> 11025 | E4: =D4*1.05 -> 11576.25 | F4: =E4*1.05 -> 12155.062 | G4: =F4*1.05 -> 12762.816 | H4: =G4*1.05 -> 13400.956 | I4: =H4*1.05 -> 14071.004 | J4: =I4*1.05 -> 14774.554 | ... M4: =L4*1.05 -> 17103.394
A5: Продажа билетов | B5: =(Items!$D$6 * Items!$D$7 * Items!$D$23)/12 -> 8333.3333 | C5: =(Items!$D$6 * Items!$D$7 * Items!$D$23)/12 -> 8333.3333 | D5: =(Items!$D$6 * Items!$D$7 * Items!$D$23)/12 -> 8333.3333 | E5: =(Items!$D$6 * Items!$D$7 * Items!$D$23)/12 -> 8333.3333 | F5: =(Items!$D$6 * Items!$D$7 * Items!$D$23)/12 -> 8333.3333 | G5: =(Items!$D$6 * Items!$D$7 * Items!$D$23)/12 -> 8333.3333 | H5: =(Items!$D$6 * Items!$D$7 * Items!$D$23)/12 -> 8333.3333 | I5: =(Items!$D$6 * Items!$D$7 * Items!$D$23)/12 -> 8333.3333 | ... M5: =(Items!$D$6 * Items!$D$7 * Items!$D$23)/12 -> 8333.3333
A6: Реклама на сайте | B6: =Items!D18 -> 1000 | C6: =B6*1.01 -> 1010 | D6: =C6*1.01 -> 1020.1 | E6: =D6*1.01 -> 1030.301 | F6: =E6*1.01 -> 1040.604 | G6: =F6*1.01 -> 1051.0101 | H6: =G6*1.01 -> 1061.5202 | I6: =H6*1.01 -> 1072.1354 | J6: =I6*1.01 -> 1082.8567 | ... M6: =L6*1.01 -> 1115.6683
A7: Реклама на выставке | B7: =(Items!$D$23 * Items!$D$19)/12 -> 333.33333 | C7: =(Items!$D$23 * Items!$D$19)/12 -> 333.33333 | D7: =(Items!$D$23 * Items!$D$19)/12 -> 333.33333 | E7: =(Items!$D$23 * Items!$D$19)/12 -> 333.33333 | F7: =(Items!$D$23 * Items!$D$19)/12 -> 333.33333 | G7: =(Items!$D$23 * Items!$D$19)/12 -> 333.33333 | H7: =(Items!$D$23 * Items!$D$19)/12 -> 333.33333 | I7: =(Items!$D$23 * Items!$D$19)/12 -> 333.33333 | ... M7: =(Items!$D$23 * Items!$D$19)/12 -> 333.33333
A8: Итого | B8: =SUM(B4:B7) -> 19666.667 | C8: =SUM(C4:C7) -> 20176.667 | D8: =SUM(D4:D7) -> 20711.767 | E8: =SUM(E4:E7) -> 21273.218 | F8: =SUM(F4:F7) -> 21862.333 | G8: =SUM(G4:G7) -> 22480.492 | H8: =SUM(H4:H7) -> 23129.143 | I8: =SUM(I4:I7) -> 23809.806 | ... M8: =SUM(M4:M7) -> 26885.729

Sheet Expenses
A1: Планируемые расходы, USD
B3: Январь | C3: Февраль | D3: Март | E3: Апрель | F3: Май | G3: Июнь | H3: Июль | I3: Август | J3: Сентябрь | K3: Октябрь | L3: Ноябрь | M3: Декабрь
A4: Разработка сайта | B4: =(Items!$D$9)/12 -> 250 | C4: =(Items!$D$9)/12 -> 250 | D4: =(Items!$D$9)/12 -> 250 | E4: =(Items!$D$9)/12 -> 250 | F4: =(Items!$D$9)/12 -> 250 | G4: =(Items!$D$9)/12 -> 250 | H4: =(Items!$D$9)/12 -> 250 | I4: =(Items!$D$9)/12 -> 250 | ... M4: =(Items!$D$9)/12 -> 250
A5: Разработка смарт-контрактов | B5: =(Items!$D$10)/12 -> 166.66667 | C5: =(Items!$D$10)/12 -> 166.66667 | D5: =(Items!$D$10)/12 -> 166.66667 | E5: =(Items!$D$10)/12 -> 166.66667 | F5: =(Items!$D$10)/12 -> 166.66667 | G5: =(Items!$D$10)/12 -> 166.66667 | H5: =(Items!$D$10)/12 -> 166.66667 | I5: =(Items!$D$10)/12 -> 166.66667 | ... M5: =(Items!$D$10)/12 -> 166.66667
A6: Деплой смарт-контрактов | B6: =(Items!$D$11)/12 -> 41.666667 | C6: =(Items!$D$11)/12 -> 41.666667 | D6: =(Items!$D$11)/12 -> 41.666667 | E6: =(Items!$D$11)/12 -> 41.666667 | F6: =(Items!$D$11)/12 -> 41.666667 | G6: =(Items!$D$11)/12 -> 41.666667 | H6: =(Items!$D$11)/12 -> 41.666667 | I6: =(Items!$D$11)/12 -> 41.666667 | ... M6: =(Items!$D$11)/12 -> 41.666667
A7: Хостинг | B7: =(Items!$D$8) -> 50 | C7: =(Items!$D$8) -> 50 | D7: =(Items!$D$8) -> 50 | E7: =(Items!$D$8) -> 50 | F7: =(Items!$D$8) -> 50 | G7: =(Items!$D$8) -> 50 | H7: =(Items!$D$8) -> 50 | I7: =(Items!$D$8) -> 50 | ... M7: =(Items!$D$8) -> 50
A8: Зарплата | B8: =(Items!$D$17) -> 6000 | C8: =(Items!$D$17) -> 6000 | D8: =(Items!$D$17) -> 6000 | E8: =(Items!$D$17) -> 6000 | F8: =(Items!$D$17) -> 6000 | G8: =(Items!$D$17) -> 6000 | H8: =(Items!$D$17) -> 6000 | I8: =(Items!$D$17) -> 6000 | ... M8: =(Items!$D$17) -> 6000
A9: Аренда | B9: =(Items!$D$14) -> 700 | C9: =(Items!$D$14) -> 700 | D9: =(Items!$D$14) -> 700 | E9: =(Items!$D$14) -> 700 | F9: =(Items!$D$14) -> 700 | G9: =(Items!$D$14) -> 700 | H9: =(Items!$D$14) -> 700 | I9: =(Items!$D$14) -> 700 | ... M9: =(Items!$D$14) -> 700
A10: Проведение выставки | B10: =(Items!$D$23 * Items!$D$22)/12 -> 2000 | C10: =(Items!$D$23 * Items!$D$22)/12 -> 2000 | D10: =(Items!$D$23 * Items!$D$22)/12 -> 2000 | E10: =(Items!$D$23 * Items!$D$22)/12 -> 2000 | F10: =(Items!$D$23 * Items!$D$22)/12 -> 2000 | G10: =(Items!$D$23 * Items!$D$22)/12 -> 2000 | H10: =(Items!$D$23 * Items!$D$22)/12 -> 2000 | I10: =(Items!$D$23 * Items!$D$22)/12 -> 2000 | ... M10: =(Items!$D$23 * Items!$D$22)/12 -> 2000
A11: Страховка | B11: =(Items!$D$21)/12 -> 2500 | C11: =(Items!$D$21)/12 -> 2500 | D11: =(Items!$D$21)/12 -> 2500 | E11: =(Items!$D$21)/12 -> 2500 | F11: =(Items!$D$21)/12 -> 2500 | G11: =(Items!$D$21)/12 -> 2500 | H11: =(Items!$D$21)/12 -> 2500 | I11: =(Items!$D$21)/12 -> 2500 | ... M11: =(Items!$D$21)/12 -> 2500
A12: Налоги | B12: =Income!B8 * Items!$D$20 -> 4326.6667 | C12: =Income!C8 * Items!$D$20 -> 4438.8667 | D12: =Income!D8 * Items!$D$20 -> 4556.5887 | E12: =Income!E8 * Items!$D$20 -> 4680.1079 | F12: =Income!F8 * Items!$D$20 -> 4809.7133 | G12: =Income!G8 * Items!$D$20 -> 4945.7083 | H12: =Income!H8 * Items!$D$20 -> 5088.4115 | I12: =Income!I8 * Items!$D$20 -> 5238.1574 | ... M12: =Income!M8 * Items!$D$20 -> 5914.8603
A13: Итого | B13: =SUM(B4:B12) -> 16035 | C13: =SUM(C4:C12) -> 16147.2 | D13: =SUM(D4:D12) -> 16264.922 | E13: =SUM(E4:E12) -> 16388.441 | F13: =SUM(F4:F12) -> 16518.047 | G13: =SUM(G4:G12) -> 16654.042 | H13: =SUM(H4:H12) -> 16796.745 | I13: =SUM(I4:I12) -> 16946.491 | ... M13: =SUM(M4:M12) -> 17623.194

Sheet Profit
A1: Планируемая прибыль, USD
B3: Январь | C3: Февраль | D3: Март | E3: Апрель | F3: Май | G3: Июнь | H3: Июль | I3: Август | J3: Сентябрь | K3: Октябрь | L3: Ноябрь | M3: Декабрь | N3: Итого
A4: Операционные доходы | B4: =Income!B8 -> 19666.667 | C4: =Income!C8 -> 20176.667 | D4: =Income!D8 -> 20711.767 | E4: =Income!E8 -> 21273.218 | F4: =Income!F8 -> 21862.333 | G4: =Income!G8 -> 22480.492 | H4: =Income!H8 -> 23129.143 | I4: =Income!I8 -> 23809.806 | ... M4: =Income!M8 -> 26885.729 | N4: =SUM(B4:M4) -> 275853.77
A5: Операционные расходы | B5: =Expenses!B13 - Expenses!B12 -> 11708.333 | C5: =Expenses!C13 - Expenses!C12 -> 11708.333 | D5: =Expenses!D13 - Expenses!D12 -> 11708.333 | E5: =Expenses!E13 - Expenses!E12 -> 11708.333 | F5: =Expenses!F13 - Expenses!F12 -> 11708.333 | G5: =Expenses!G13 - Expenses!G12 -> 11708.333 | H5: =Expenses!H13 - Expenses!H12 -> 11708.333 | I5: =Expenses!I13 - Expenses!I12 -> 11708.333 | ... M5: =Expenses!M13 - Expenses!M12 -> 11708.333 | N5: =SUM(B5:M5) -> 140500
A6: Операционная прибыль | B6: =B4-B5 -> 7958.3333 | C6: =C4-C5 -> 8468.3333 | D6: =D4-D5 -> 9003.4333 | E6: =E4-E5 -> 9564.8843 | F6: =F4-F5 -> 10154 | G6: =G4-G5 -> 10772.159 | H6: =H4-H5 -> 11420.81 | I6: =I4-I5 -> 12101.473 | ... M6: =M4-M5 -> 15177.395 | N6: =SUM(B6:M6) -> 135353.77
A7: Чистая прибыль | B7: =B6-Expenses!B12 -> 3631.6667 | C7: =C6-Expenses!C12 -> 4029.4667 | D7: =D6-Expenses!D12 -> 4446.8447 | E7: =E6-Expenses!E12 -> 4884.7764 | F7: =F6-Expenses!F12 -> 5344.2865 | G7: =G6-Expenses!G12 -> 5826.4507 | H7: =H6-Expenses!H12 -> 6332.3984 | I7: =I6-Expenses!I12 -> 6863.3155 | ... M7: =M6-Expenses!M12 -> 9262.535 | N7: =SUM(B7:M7) -> 74665.939
A8: Рентабельность продаж (ROS) | B8: =B7/B4 -> 0.18466102 | C8: =C7/C4 -> 0.19970924 | D8: =D7/D4 -> 0.21470137 | E8: =E7/E4 -> 0.22962095 | F8: =F7/F4 -> 0.24445179 | G8: =G7/G4 -> 0.25917807 | H8: =H7/H4 -> 0.27378439 | I8: =I7/I4 -> 0.28825583 | ... N8: =N7/N4 -> 0.27067217
A9: Рентабельность продукции (ROM) | B9: =B6/B4 -> 0.40466102 | C9: =C6/C4 -> 0.41970924 | D9: =D6/D4 -> 0.43470137 | E9: =E6/E4 -> 0.44962095 | F9: =F6/F4 -> 0.46445179 | G9: =G6/G4 -> 0.47917807 | H9: =H6/H4 -> 0.49378439 | I9: =I6/I4 -> 0.50825583 | ... N9: =N6/N4 -> 0.49067217
A10: Рентабельность инвестиций (ROI) | B10: =(B7-(Expenses!B4+Expenses!B5+Expenses!B6+Expenses!B7+Expenses!B10))/(Expenses!B4+Expenses!B5+Expenses!B6+Expenses!B7+Expenses!B10) -> 0.44784053 | C10: =(C7-(Expenses!C4+Expenses!C5+Expenses!C6+Expenses!C7+Expenses!C10))/(Expenses!C4+Expenses!C5+Expenses!C6+Expenses!C7+Expenses!C10) -> 0.60643189 | D10: =(D7-(Expenses!D4+Expenses!D5+Expenses!D6+Expenses!D7+Expenses!D10))/(Expenses!D4+Expenses!D5+Expenses!D6+Expenses!D7+Expenses!D10) -> 0.77282844 | E10: =(E7-(Expenses!E4+Expenses!E5+Expenses!E6+Expenses!E7+Expenses!E10))/(Expenses!E4+Expenses!E5+Expenses!E6+Expenses!E7+Expenses!E10) -> 0.94741918 | F10: =(F7-(Expenses!F4+Expenses!F5+Expenses!F6+Expenses!F7+Expenses!F10))/(Expenses!F4+Expenses!F5+Expenses!F6+Expenses!F7+Expenses!F10) -> 1.1306126 | G10: =(G7-(Expenses!G4+Expenses!G5+Expenses!G6+Expenses!G7+Expenses!G10))/(Expenses!G4+Expenses!G5+Expenses!G6+Expenses!G7+Expenses!G10) -> 1.3228375 | H10: =(H7-(Expenses!H4+Expenses!H5+Expenses!H6+Expenses!H7+Expenses!H10))/(Expenses!H4+Expenses!H5+Expenses!H6+Expenses!H7+Expenses!H10) -> 1.5245442 | I10: =(I7-(Expenses!I4+Expenses!I5+Expenses!I6+Expenses!I7+Expenses!I10))/(Expenses!I4+Expenses!I5+Expenses!I6+Expenses!I7+Expenses!I10) -> 1.7362055 | ... M10: =(M7-(Expenses!M4+Expenses!M5+Expenses!M6+Expenses!M7+Expenses!M10))/(Expenses!M4+Expenses!M5+Expenses!M6+Expenses!M7+Expenses!M10) -> 2.692705
A11: Прибыль нарастающим итогом | B11: =B6 -> 7958.3333 | C11: =B11+C6 -> 16426.667 | D11: =C11+D6 -> 25430.1 | E11: =D11+E6 -> 34994.984 | F11: =E11+F6 -> 45148.984 | G11: =F11+G6 -> 55921.143 | H11: =G11+H6 -> 67341.953 | I11: =H11+I6 -> 79443.426 | J11: =I11+J6 -> 92259.17 | ... M11: =L11+M6 -> 135353.77

Sheet Cash flow
A1: План движения денежных средств, USD
A3: Показатели | B3: Январь | C3: Февраль | D3: Март | E3: Апрель | F3: Май | G3: Июнь | H3: Июль | I3: Август | J3: Сентябрь | K3: Октябрь | L3: Ноябрь | M3: Декабрь
A4: Поступления по операционной деятельности | B4: =Profit!B4 -> 19666.667 | C4: =Profit!C4 -> 20176.667 | D4: =Profit!D4 -> 20711.767 | E4: =Profit!E4 -> 21273.218 | F4: =Profit!F4 -> 21862.333 | G4: =Profit!G4 -> 22480.492 | H4: =Profit!H4 -> 23129.143 | I4: =Profit!I4 -> 23809.806 | ... M4: =Profit!M4 -> 26885.729
A5: Платежи по операционной деятельности | B5: =SUM(B6:B13) -> 5708.3333 | C5: =SUM(C6:C13) -> 11708.333 | D5: =SUM(D6:D13) -> 11708.333 | E5: =SUM(E6:E13) -> 11708.333 | F5: =SUM(F6:F13) -> 11708.333 | G5: =SUM(G6:G13) -> 11708.333 | H5: =SUM(H6:H13) -> 11708.333 | I5: =SUM(I6:I13) -> 11708.333 | ... M5: =SUM(M6:M13) -> 11708.333
A6: Разработка сайта | B6: =Expenses!B4 -> 250 | C6: =Expenses!C4 -> 250 | D6: =Expenses!D4 -> 250 | E6: =Expenses!E4 -> 250 | F6: =Expenses!F4 -> 250 | G6: =Expenses!G4 -> 250 | H6: =Expenses!H4 -> 250 | I6: =Expenses!I4 -> 250 | ... M6: =Expenses!M4 -> 250
A7: Разработка смарт-контрактов | B7: =Expenses!B5 -> 166.66667 | C7: =Expenses!C5 -> 166.66667 | D7: =Expenses!D5 -> 166.66667 | E7: =Expenses!E5 -> 166.66667 | F7: =Expenses!F5 -> 166.66667 | G7: =Expenses!G5 -> 166.66667 | H7: =Expenses!H5 -> 166.66667 | I7: =Expenses!I5 -> 166.66667 | ... M7: =Expenses!M5 -> 166.66667
A8: Деплой смарт-контрактов | B8: =Expenses!B6 -> 41.666667 | C8: =Expenses!C6 -> 41.666667 | D8: =Expenses!D6 -> 41.666667 | E8: =Expenses!E6 -> 41.666667 | F8: =Expenses!F6 -> 41.666667 | G8: =Expenses!G6 -> 41.666667 | H8: =Expenses!H6 -> 41.666667 | I8: =Expenses!I6 -> 41.666667 | ... M8: =Expenses!M6 -> 41.666667
A9: Хостинг | B9: =Expenses!B7 -> 50 | C9: =Expenses!C7 -> 50 | D9: =Expenses!D7 -> 50 | E9: =Expenses!E7 -> 50 | F9: =Expenses!F7 -> 50 | G9: =Expenses!G7 -> 50 | H9: =Expenses!H7 -> 50 | I9: =Expenses!I7 -> 50 | ... M9: =Expenses!M7 -> 50
A10: Зарплата | B10: 0 | C10: =Expenses!B8 -> 6000 | D10: =Expenses!C8 -> 6000 | E10: =Expenses!D8 -> 6000 | F10: =Expenses!E8 -> 6000 | G10: =Expenses!F8 -> 6000 | H10: =Expenses!G8 -> 6000 | I10: =Expenses!H8 -> 6000 | J10: =Expenses!I8 -> 6000 | ... M10: =Expenses!L8 -> 6000
A11: Аренда | B11: =Expenses!B9 -> 700 | C11: =Expenses!C9 -> 700 | D11: =Expenses!D9 -> 700 | E11: =Expenses!E9 -> 700 | F11: =Expenses!F9 -> 700 | G11: =Expenses!G9 -> 700 | H11: =Expenses!H9 -> 700 | I11: =Expenses!I9 -> 700 | ... M11: =Expenses!M9 -> 700
A12: Проведение выставки | B12: =Expenses!B10 -> 2000 | C12: =Expenses!C10 -> 2000 | D12: =Expenses!D10 -> 2000 | E12: =Expenses!E10 -> 2000 | F12: =Expenses!F10 -> 2000 | G12: =Expenses!G10 -> 2000 | H12: =Expenses!H10 -> 2000 | I12: =Expenses!I10 -> 2000 | ... M12: =Expenses!M10 -> 2000
A13: Страховка | B13: =Expenses!B11 -> 2500 | C13: =Expenses!C11 -> 2500 | D13: =Expenses!D11 -> 2500 | E13: =Expenses!E11 -> 2500 | F13: =Expenses!F11 -> 2500 | G13: =Expenses!G11 -> 2500 | H13: =Expenses!H11 -> 2500 | I13: =Expenses!I11 -> 2500 | ... M13: =Expenses!M11 -> 2500
A14: Сальдо по операционной деятельности | B14: =B4-B5 -> 13958.333 | C14: =C4-C5 -> 8468.3333 | D14: =D4-D5 -> 9003.4333 | E14: =E4-E5 -> 9564.8843 | F14: =F4-F5 -> 10154 | G14: =G4-G5 -> 10772.159 | H14: =H4-H5 -> 11420.81 | I14: =I4-I5 -> 12101.473 | ... M14: =M4-M5 -> 15177.395
A15: Сальдо на начало периода | B15: 0 | C15: =B16 -> 13958.333 | D15: =C16 -> 22426.667 | E15: =D16 -> 31430.1 | F15: =E16 -> 40994.984 | G15: =F16 -> 51148.984 | H15: =G16 -> 61921.143 | I15: =H16 -> 73341.953 | J15: =I16 -> 85443.426 | ... M15: =L16 -> 126176.37
A16: Сальдо на конец периода | B16: =B14 -> 13958.333 | C16: =C15+C14 -> 22426.667 | D16: =D15+D14 -> 31430.1 | E16: =E15+E14 -> 40994.984 | F16: =F15+F14 -> 51148.984 | G16: =G15+G14 -> 61921.143 | H16: =H15+H14 -> 73341.953 | I16: =I15+I14 -> 85443.426 | J16: =J15+J14 -> 98259.17 | ... M16: =M15+M14 -> 141353.77

Sheet Predict balance
A1: Прогнозируемый баланс, USD
A3: Показатели | B3: 46023 | C3: 46054 | D3: 46082 | E3: 46113 | F3: 46143 | G3: 46174 | H3: 46204 | I3: 46235 | J3: 46266 | K3: 46296 | L3: 46327 | M3: 46357 | N3: 46388
A4: Денежные средства | B4: ='Cash flow'!B15 -> 0 | C4: ='Cash flow'!B16 -> 13958.333 | D4: ='Cash flow'!C16 -> 22426.667 | E4: ='Cash flow'!D16 -> 31430.1 | F4: ='Cash flow'!E16 -> 40994.984 | G4: ='Cash flow'!F16 -> 51148.984 | H4: ='Cash flow'!G16 -> 61921.143 | I4: ='Cash flow'!H16 -> 73341.953 | J4: ='Cash flow'!I16 -> 85443.426 | ... N4: ='Cash flow'!M16 -> 141353.77
A5: Дебюторская заложность | B5: 0 | C5: 0 | D5: 0 | E5: 0 | F5: 0 | G5: 0 | H5: 0 | I5: 0 | J5: 0 | K5: 0 | L5: 0 | M5: 0 | N5: 0
A6: Активы, итого | B6: =SUM(B4:B5) -> 0 | C6: =SUM(C4:C5) -> 13958.333 | D6: =SUM(D4:D5) -> 22426.667 | E6: =SUM(E4:E5) -> 31430.1 | F6: =SUM(F4:F5) -> 40994.984 | G6: =SUM(G4:G5) -> 51148.984 | H6: =SUM(H4:H5) -> 61921.143 | I6: =SUM(I4:I5) -> 73341.953 | ... N6: =SUM(N4:N5) -> 141353.77
A7: Кредиторская задолжность | B7: 0 | C7: =B7+Expenses!B8-'Cash flow'!B10 -> 6000 | D7: =C7+Expenses!C8-'Cash flow'!C10 -> 6000 | E7: =D7+Expenses!D8-'Cash flow'!D10 -> 6000 | F7: =E7+Expenses!E8-'Cash flow'!E10 -> 6000 | G7: =F7+Expenses!F8-'Cash flow'!F10 -> 6000 | H7: =G7+Expenses!G8-'Cash flow'!G10 -> 6000 | I7: =H7+Expenses!H8-'Cash flow'!H10 -> 6000 | J7: =I7+Expenses!I8-'Cash flow'!I10 -> 6000 | ... N7: =M7+Expenses!M8-'Cash flow'!M10 -> 6000
A8: Капитал | B8: 0 | C8: =B8+Profit!B6 -> 7958.3333 | D8: =C8+Profit!C6 -> 16426.667 | E8: =D8+Profit!D6 -> 25430.1 | F8: =E8+Profit!E6 -> 34994.984 | G8: =F8+Profit!F6 -> 45148.984 | H8: =G8+Profit!G6 -> 55921.143 | I8: =H8+Profit!H6 -> 67341.953 | J8: =I8+Profit!I6 -> 79443.426 | ... N8: =M8+Profit!M6 -> 135353.77
A9: Пассивы, итого | B9: =SUM(B7:B8) -> 0 | C9: =SUM(C7:C8) -> 13958.333 | D9: =SUM(D7:D8) -> 22426.667 | E9: =SUM(E7:E8) -> 31430.1 | F9: =SUM(F7:F8) -> 40994.984 | G9: =SUM(G7:G8) -> 51148.984 | H9: =SUM(H7:H8) -> 61921.143 | I9: =SUM(I7:I8) -> 73341.953 | ... N9: =SUM(N7:N8) -> 141353.77
